{
    "clientName": "Hortonworks, Inc.",
    "salesForceProjectName": "Sprint FLUX Migration",
    "region": "MW-CHI",
    "practice": "Big Data",
    "_createProjManager": "Phil Favia",
    "startDate": "2016-02-23",
    "endDate": "2016-06-30",
    "salesforceRecordId": "a1D70000002jeGW",
    "projectDisplayName": "Sprint FLUX Migration",
    "positions": [
        {
            "assignmentName": "Sprint FLUX Migration - Pat Morrison",
            "filledBy": [
                {
                    "userFullName": "Pat Morrison",
                    "startDate": "2016-02-23",
                    "endDate": "2016-06-30"
                }
            ]
        }
    ]
}