{
    "clientName": "Patheos",
    "salesForceProjectName": "WordPress Update",
    "region": "NATL",
    "practice": "Enterprise Web",
    "_createProjManager": "John Holshey",
    "startDate": "2016-01-18",
    "endDate": "2016-02-26",
    "salesforceRecordId": "a1D39000003R0Qu",
    "projectDisplayName": "WordPress Update",
    "positions": [
        {
            "assignmentName": "WordPress Update-Abe Becker",
            "filledBy": [
                {
                    "userFullName": "Abe Becker",
                    "startDate": "2016-01-18",
                    "endDate": "2016-02-26"
                }
            ]
        },
        {
            "assignmentName": "WordPress Update-Manjesh Reddy",
            "filledBy": [
                {
                    "userFullName": "Manjesh Reddy",
                    "startDate": "2016-01-18",
                    "endDate": "2016-02-26"
                }
            ]
        },
        {
            "assignmentName": "WordPress Update - Matt Ross",
            "filledBy": [
                {
                    "userFullName": "Matt Ross",
                    "startDate": "2016-01-18",
                    "endDate": "2016-04-12"
                }
            ]
        }
    ]
}